utbot_executor/__init__.py
utbot_executor/__main__.py
utbot_executor/config.py
utbot_executor/deep_serialization/__init__.py
utbot_executor/deep_serialization/config.py
utbot_executor/deep_serialization/deep_serialization.py
utbot_executor/deep_serialization/example.py
utbot_executor/deep_serialization/iterator_wrapper.py
utbot_executor/deep_serialization/json_converter.py
utbot_executor/deep_serialization/memory_objects.py
utbot_executor/deep_serialization/test_json.json
utbot_executor/deep_serialization/utils.py
utbot_executor/executor.py
utbot_executor/listener.py
utbot_executor/memory_compressor.py
utbot_executor/parser.py
utbot_executor/ut_tracer.py
utbot_executor/utils.py
utbot_executor-1.10.0.dist-info/entry_points.txt
utbot_executor-1.10.0.dist-info/METADATA
utbot_executor-1.10.0.dist-info/WHEEL
utbot_executor-1.10.0.dist-info/RECORD
