Metadata-Version: 2.1
Name: utbot-executor
Version: 1.10.0
Summary: 
Author: Vyacheslav Tamarin
Author-email: vyacheslav.tamarin@yandex.ru
Requires-Python: >=3.8,<4.0
Classifier: Programming Language :: Python :: 3
Classifier: Programming Language :: Python :: 3.8
Classifier: Programming Language :: Python :: 3.9
Classifier: Programming Language :: Python :: 3.10
Classifier: Programming Language :: Python :: 3.11
Classifier: Programming Language :: Python :: 3.12
